{
  "fetched_at": 1783287761,
  "radius_km": 50.0,
  "total_ships": 17,
  "by_beach": {
    "copa-p5": [
      {
        "mmsi": 710003050,
        "name": "ASSO VENTISETTE",
        "type": "—",
        "type_code": null,
        "status": "atracado",
        "speed_kn": 0,
        "heading": 155,
        "dest": null,
        "callsign": null,
        "lat": -22.8945,
        "lng": -43.2122,
        "dist_km": 9.9,
        "bearing": 347,
        "compass": "N",
        "last_seen": 1783287741
      },
      {
        "mmsi": 710000391,
        "name": "WEZEN",
        "type": "—",
        "type_code": null,
        "status": "—",
        "speed_kn": 0,
        "heading": null,
        "dest": null,
        "callsign": null,
        "lat": -22.8921,
        "lng": -43.1907,
        "dist_km": 10.0,
        "bearing": 0,
        "compass": "N",
        "last_seen": 1783287670
      },
      {
        "mmsi": 710018340,
        "name": "WS PEGASUS",
        "type": "—",
        "type_code": null,
        "status": "navegando",
        "speed_kn": 0.1,
        "heading": null,
        "dest": null,
        "callsign": null,
        "lat": -22.892,
        "lng": -43.1906,
        "dist_km": 10.0,
        "bearing": 0,
        "compass": "N",
        "last_seen": 1783287679
      },
      {
        "mmsi": 710000009,
        "name": "HERCULES",
        "type": "—",
        "type_code": null,
        "status": "navegando",
        "speed_kn": 0,
        "heading": null,
        "dest": null,
        "callsign": null,
        "lat": -22.892,
        "lng": -43.1941,
        "dist_km": 10.0,
        "bearing": 358,
        "compass": "N",
        "last_seen": 1783287703
      },
      {
        "mmsi": 710019710,
        "name": "URCA III",
        "type": "—",
        "type_code": null,
        "status": "navegando",
        "speed_kn": 8.6,
        "heading": null,
        "dest": null,
        "callsign": null,
        "lat": -22.8969,
        "lng": -43.1511,
        "dist_km": 10.3,
        "bearing": 23,
        "compass": "NE",
        "last_seen": 1783287704
      },
      {
        "mmsi": 710005627,
        "name": "CBO MISTRAL",
        "type": "—",
        "type_code": null,
        "status": "atracado",
        "speed_kn": 0,
        "heading": 334,
        "dest": null,
        "callsign": null,
        "lat": -22.8915,
        "lng": -43.2138,
        "dist_km": 10.3,
        "bearing": 347,
        "compass": "N",
        "last_seen": 1783287730
      },
      {
        "mmsi": 710024740,
        "name": "SULIS",
        "type": "—",
        "type_code": null,
        "status": "navegando",
        "speed_kn": 0,
        "heading": null,
        "dest": null,
        "callsign": null,
        "lat": -22.8703,
        "lng": -43.2131,
        "dist_km": 12.6,
        "bearing": 350,
        "compass": "N",
        "last_seen": 1783287686
      },
      {
        "mmsi": 710015310,
        "name": "ARTHUR",
        "type": "—",
        "type_code": null,
        "status": "navegando",
        "speed_kn": 0,
        "heading": null,
        "dest": null,
        "callsign": null,
        "lat": -22.8701,
        "lng": -43.2128,
        "dist_km": 12.6,
        "bearing": 350,
        "compass": "N",
        "last_seen": 1783287729
      },
      {
        "mmsi": 710001593,
        "name": "SAAM HOLANDA",
        "type": "—",
        "type_code": null,
        "status": "navegando",
        "speed_kn": 0,
        "heading": null,
        "dest": null,
        "callsign": null,
        "lat": -22.8699,
        "lng": -43.2127,
        "dist_km": 12.6,
        "bearing": 350,
        "compass": "N",
        "last_seen": 1783287729
      },
      {
        "mmsi": 710012550,
        "name": "SAAM PATAXO",
        "type": "—",
        "type_code": null,
        "status": "navegando",
        "speed_kn": 0,
        "heading": null,
        "dest": null,
        "callsign": null,
        "lat": -22.8702,
        "lng": -43.2132,
        "dist_km": 12.6,
        "bearing": 349,
        "compass": "N",
        "last_seen": 1783287745
      },
      {
        "mmsi": 710016030,
        "name": "LANCELOT",
        "type": "—",
        "type_code": null,
        "status": "navegando",
        "speed_kn": 0,
        "heading": null,
        "dest": null,
        "callsign": null,
        "lat": -22.87,
        "lng": -43.2129,
        "dist_km": 12.6,
        "bearing": 350,
        "compass": "N",
        "last_seen": 1783287750
      },
      {
        "mmsi": 710018820,
        "name": "C SEPETIBA",
        "type": "—",
        "type_code": null,
        "status": "navegando",
        "speed_kn": 0,
        "heading": 152,
        "dest": null,
        "callsign": null,
        "lat": -22.8741,
        "lng": -43.1217,
        "dist_km": 13.9,
        "bearing": 31,
        "compass": "NE",
        "last_seen": 1783287756
      },
      {
        "mmsi": 710008330,
        "name": "C MACAE",
        "type": "—",
        "type_code": null,
        "status": "—",
        "speed_kn": 0.5,
        "heading": null,
        "dest": null,
        "callsign": null,
        "lat": -22.9743,
        "lng": -43.054,
        "dist_km": 14.0,
        "bearing": 87,
        "compass": "L",
        "last_seen": 1783287745
      },
      {
        "mmsi": 710027960,
        "name": "BARU TESORO",
        "type": "—",
        "type_code": null,
        "status": "navegando",
        "speed_kn": 0.1,
        "heading": 324,
        "dest": null,
        "callsign": null,
        "lat": -22.8493,
        "lng": -43.1797,
        "dist_km": 14.8,
        "bearing": 4,
        "compass": "N",
        "last_seen": 1783287721
      },
      {
        "mmsi": 352002481,
        "name": "BARU SIERRA NEVADA",
        "type": "—",
        "type_code": null,
        "status": "ancorado",
        "speed_kn": 102.3,
        "heading": 218,
        "dest": null,
        "callsign": null,
        "lat": -22.8483,
        "lng": -43.1303,
        "dist_km": 16.1,
        "bearing": 23,
        "compass": "NE",
        "last_seen": 1783287717
      }
    ],
    "morro-terceira": [],
    "sao-conrado": [
      {
        "mmsi": 710003050,
        "name": "ASSO VENTISETTE",
        "type": "—",
        "type_code": null,
        "status": "atracado",
        "speed_kn": 0,
        "heading": 155,
        "dest": null,
        "callsign": null,
        "lat": -22.8945,
        "lng": -43.2122,
        "dist_km": 13.3,
        "bearing": 25,
        "compass": "NE",
        "last_seen": 1783287741
      },
      {
        "mmsi": 710005627,
        "name": "CBO MISTRAL",
        "type": "—",
        "type_code": null,
        "status": "atracado",
        "speed_kn": 0,
        "heading": 334,
        "dest": null,
        "callsign": null,
        "lat": -22.8915,
        "lng": -43.2138,
        "dist_km": 13.5,
        "bearing": 24,
        "compass": "NE",
        "last_seen": 1783287730
      },
      {
        "mmsi": 710000009,
        "name": "HERCULES",
        "type": "—",
        "type_code": null,
        "status": "navegando",
        "speed_kn": 0,
        "heading": null,
        "dest": null,
        "callsign": null,
        "lat": -22.892,
        "lng": -43.1941,
        "dist_km": 14.4,
        "bearing": 32,
        "compass": "NE",
        "last_seen": 1783287703
      },
      {
        "mmsi": 710000391,
        "name": "WEZEN",
        "type": "—",
        "type_code": null,
        "status": "—",
        "speed_kn": 0,
        "heading": null,
        "dest": null,
        "callsign": null,
        "lat": -22.8921,
        "lng": -43.1907,
        "dist_km": 14.6,
        "bearing": 33,
        "compass": "NE",
        "last_seen": 1783287670
      },
      {
        "mmsi": 710018340,
        "name": "WS PEGASUS",
        "type": "—",
        "type_code": null,
        "status": "navegando",
        "speed_kn": 0.1,
        "heading": null,
        "dest": null,
        "callsign": null,
        "lat": -22.892,
        "lng": -43.1906,
        "dist_km": 14.6,
        "bearing": 33,
        "compass": "NE",
        "last_seen": 1783287679
      },
      {
        "mmsi": 710024740,
        "name": "SULIS",
        "type": "—",
        "type_code": null,
        "status": "navegando",
        "speed_kn": 0,
        "heading": null,
        "dest": null,
        "callsign": null,
        "lat": -22.8703,
        "lng": -43.2131,
        "dist_km": 15.7,
        "bearing": 21,
        "compass": "N",
        "last_seen": 1783287686
      },
      {
        "mmsi": 710012550,
        "name": "SAAM PATAXO",
        "type": "—",
        "type_code": null,
        "status": "navegando",
        "speed_kn": 0,
        "heading": null,
        "dest": null,
        "callsign": null,
        "lat": -22.8702,
        "lng": -43.2132,
        "dist_km": 15.7,
        "bearing": 21,
        "compass": "N",
        "last_seen": 1783287745
      },
      {
        "mmsi": 710015310,
        "name": "ARTHUR",
        "type": "—",
        "type_code": null,
        "status": "navegando",
        "speed_kn": 0,
        "heading": null,
        "dest": null,
        "callsign": null,
        "lat": -22.8701,
        "lng": -43.2128,
        "dist_km": 15.8,
        "bearing": 21,
        "compass": "N",
        "last_seen": 1783287729
      },
      {
        "mmsi": 710001593,
        "name": "SAAM HOLANDA",
        "type": "—",
        "type_code": null,
        "status": "navegando",
        "speed_kn": 0,
        "heading": null,
        "dest": null,
        "callsign": null,
        "lat": -22.8699,
        "lng": -43.2127,
        "dist_km": 15.8,
        "bearing": 21,
        "compass": "N",
        "last_seen": 1783287729
      },
      {
        "mmsi": 710016030,
        "name": "LANCELOT",
        "type": "—",
        "type_code": null,
        "status": "navegando",
        "speed_kn": 0,
        "heading": null,
        "dest": null,
        "callsign": null,
        "lat": -22.87,
        "lng": -43.2129,
        "dist_km": 15.8,
        "bearing": 21,
        "compass": "N",
        "last_seen": 1783287750
      },
      {
        "mmsi": 710019710,
        "name": "URCA III",
        "type": "—",
        "type_code": null,
        "status": "navegando",
        "speed_kn": 8.6,
        "heading": null,
        "dest": null,
        "callsign": null,
        "lat": -22.8969,
        "lng": -43.1511,
        "dist_km": 16.8,
        "bearing": 46,
        "compass": "NE",
        "last_seen": 1783287704
      },
      {
        "mmsi": 710027960,
        "name": "BARU TESORO",
        "type": "—",
        "type_code": null,
        "status": "navegando",
        "speed_kn": 0.1,
        "heading": 324,
        "dest": null,
        "callsign": null,
        "lat": -22.8493,
        "lng": -43.1797,
        "dist_km": 19.3,
        "bearing": 28,
        "compass": "NE",
        "last_seen": 1783287721
      },
      {
        "mmsi": 710018820,
        "name": "C SEPETIBA",
        "type": "—",
        "type_code": null,
        "status": "navegando",
        "speed_kn": 0,
        "heading": 152,
        "dest": null,
        "callsign": null,
        "lat": -22.8741,
        "lng": -43.1217,
        "dist_km": 20.7,
        "bearing": 46,
        "compass": "NE",
        "last_seen": 1783287756
      },
      {
        "mmsi": 710008330,
        "name": "C MACAE",
        "type": "—",
        "type_code": null,
        "status": "—",
        "speed_kn": 0.5,
        "heading": null,
        "dest": null,
        "callsign": null,
        "lat": -22.9743,
        "lng": -43.054,
        "dist_km": 22.1,
        "bearing": 82,
        "compass": "L",
        "last_seen": 1783287745
      },
      {
        "mmsi": 352002481,
        "name": "BARU SIERRA NEVADA",
        "type": "—",
        "type_code": null,
        "status": "ancorado",
        "speed_kn": 102.3,
        "heading": 218,
        "dest": null,
        "callsign": null,
        "lat": -22.8483,
        "lng": -43.1303,
        "dist_km": 22.2,
        "bearing": 39,
        "compass": "NE",
        "last_seen": 1783287717
      }
    ],
    "leblon-mirante": [
      {
        "mmsi": 710003050,
        "name": "ASSO VENTISETTE",
        "type": "—",
        "type_code": null,
        "status": "atracado",
        "speed_kn": 0,
        "heading": 155,
        "dest": null,
        "callsign": null,
        "lat": -22.8945,
        "lng": -43.2122,
        "dist_km": 10.5,
        "bearing": 6,
        "compass": "N",
        "last_seen": 1783287741
      },
      {
        "mmsi": 710005627,
        "name": "CBO MISTRAL",
        "type": "—",
        "type_code": null,
        "status": "atracado",
        "speed_kn": 0,
        "heading": 334,
        "dest": null,
        "callsign": null,
        "lat": -22.8915,
        "lng": -43.2138,
        "dist_km": 10.9,
        "bearing": 5,
        "compass": "N",
        "last_seen": 1783287730
      },
      {
        "mmsi": 710000391,
        "name": "WEZEN",
        "type": "—",
        "type_code": null,
        "status": "—",
        "speed_kn": 0,
        "heading": null,
        "dest": null,
        "callsign": null,
        "lat": -22.8921,
        "lng": -43.1907,
        "dist_km": 11.2,
        "bearing": 17,
        "compass": "N",
        "last_seen": 1783287670
      },
      {
        "mmsi": 710000009,
        "name": "HERCULES",
        "type": "—",
        "type_code": null,
        "status": "navegando",
        "speed_kn": 0,
        "heading": null,
        "dest": null,
        "callsign": null,
        "lat": -22.892,
        "lng": -43.1941,
        "dist_km": 11.2,
        "bearing": 15,
        "compass": "N",
        "last_seen": 1783287703
      },
      {
        "mmsi": 710018340,
        "name": "WS PEGASUS",
        "type": "—",
        "type_code": null,
        "status": "navegando",
        "speed_kn": 0.1,
        "heading": null,
        "dest": null,
        "callsign": null,
        "lat": -22.892,
        "lng": -43.1906,
        "dist_km": 11.3,
        "bearing": 17,
        "compass": "N",
        "last_seen": 1783287679
      },
      {
        "mmsi": 710019710,
        "name": "URCA III",
        "type": "—",
        "type_code": null,
        "status": "navegando",
        "speed_kn": 8.6,
        "heading": null,
        "dest": null,
        "callsign": null,
        "lat": -22.8969,
        "lng": -43.1511,
        "dist_km": 12.6,
        "bearing": 36,
        "compass": "NE",
        "last_seen": 1783287704
      },
      {
        "mmsi": 710024740,
        "name": "SULIS",
        "type": "—",
        "type_code": null,
        "status": "navegando",
        "speed_kn": 0,
        "heading": null,
        "dest": null,
        "callsign": null,
        "lat": -22.8703,
        "lng": -43.2131,
        "dist_km": 13.2,
        "bearing": 4,
        "compass": "N",
        "last_seen": 1783287686
      },
      {
        "mmsi": 710015310,
        "name": "ARTHUR",
        "type": "—",
        "type_code": null,
        "status": "navegando",
        "speed_kn": 0,
        "heading": null,
        "dest": null,
        "callsign": null,
        "lat": -22.8701,
        "lng": -43.2128,
        "dist_km": 13.2,
        "bearing": 5,
        "compass": "N",
        "last_seen": 1783287729
      },
      {
        "mmsi": 710012550,
        "name": "SAAM PATAXO",
        "type": "—",
        "type_code": null,
        "status": "navegando",
        "speed_kn": 0,
        "heading": null,
        "dest": null,
        "callsign": null,
        "lat": -22.8702,
        "lng": -43.2132,
        "dist_km": 13.2,
        "bearing": 4,
        "compass": "N",
        "last_seen": 1783287745
      },
      {
        "mmsi": 710016030,
        "name": "LANCELOT",
        "type": "—",
        "type_code": null,
        "status": "navegando",
        "speed_kn": 0,
        "heading": null,
        "dest": null,
        "callsign": null,
        "lat": -22.87,
        "lng": -43.2129,
        "dist_km": 13.2,
        "bearing": 4,
        "compass": "N",
        "last_seen": 1783287750
      },
      {
        "mmsi": 710001593,
        "name": "SAAM HOLANDA",
        "type": "—",
        "type_code": null,
        "status": "navegando",
        "speed_kn": 0,
        "heading": null,
        "dest": null,
        "callsign": null,
        "lat": -22.8699,
        "lng": -43.2127,
        "dist_km": 13.3,
        "bearing": 5,
        "compass": "N",
        "last_seen": 1783287729
      },
      {
        "mmsi": 710027960,
        "name": "BARU TESORO",
        "type": "—",
        "type_code": null,
        "status": "navegando",
        "speed_kn": 0.1,
        "heading": 324,
        "dest": null,
        "callsign": null,
        "lat": -22.8493,
        "lng": -43.1797,
        "dist_km": 16.1,
        "bearing": 16,
        "compass": "N",
        "last_seen": 1783287721
      },
      {
        "mmsi": 710018820,
        "name": "C SEPETIBA",
        "type": "—",
        "type_code": null,
        "status": "navegando",
        "speed_kn": 0,
        "heading": 152,
        "dest": null,
        "callsign": null,
        "lat": -22.8741,
        "lng": -43.1217,
        "dist_km": 16.4,
        "bearing": 39,
        "compass": "NE",
        "last_seen": 1783287756
      },
      {
        "mmsi": 710008330,
        "name": "C MACAE",
        "type": "—",
        "type_code": null,
        "status": "—",
        "speed_kn": 0.5,
        "heading": null,
        "dest": null,
        "callsign": null,
        "lat": -22.9743,
        "lng": -43.054,
        "dist_km": 17.4,
        "bearing": 85,
        "compass": "L",
        "last_seen": 1783287745
      },
      {
        "mmsi": 352002481,
        "name": "BARU SIERRA NEVADA",
        "type": "—",
        "type_code": null,
        "status": "ancorado",
        "speed_kn": 102.3,
        "heading": 218,
        "dest": null,
        "callsign": null,
        "lat": -22.8483,
        "lng": -43.1303,
        "dist_km": 18.3,
        "bearing": 31,
        "compass": "NE",
        "last_seen": 1783287717
      }
    ],
    "balneario-rincao": [],
    "praia-grande-boqueirao": [],
    "cabo-frio-forte": [],
    "balneario-camboriu": [],
    "santos-gonzaga": [],
    "guaruja-enseada": [],
    "floripa-barra-lagoa": [],
    "natal-ponta-negra": []
  }
}